streamlit_dash/__init__.py
streamlit_dash/frontend/.env
streamlit_dash/frontend/.prettierrc
streamlit_dash/frontend/build/asset-manifest.json
streamlit_dash/frontend/build/index.html
streamlit_dash/frontend/build/precache-manifest.333968c81367d442b90c2c407970109b.js
streamlit_dash/frontend/build/service-worker.js
streamlit_dash/frontend/build/static/js/2.451b2942.chunk.js
streamlit_dash/frontend/build/static/js/2.451b2942.chunk.js.LICENSE.txt
streamlit_dash/frontend/build/static/js/2.451b2942.chunk.js.map
streamlit_dash/frontend/build/static/js/main.c396fd5a.chunk.js
streamlit_dash/frontend/build/static/js/main.c396fd5a.chunk.js.map
streamlit_dash/frontend/build/static/js/runtime-main.58369df8.js
streamlit_dash/frontend/build/static/js/runtime-main.58369df8.js.map
streamlit_dash/frontend/build/styles.css
streamlit_dash/frontend/package-lock.json
streamlit_dash/frontend/package.json
streamlit_dash/frontend/public/index.html
streamlit_dash/frontend/public/styles.css
streamlit_dash/frontend/src/index.tsx
streamlit_dash/frontend/src/react-app-env.d.ts
streamlit_dash/frontend/tsconfig.json
streamlit_dash-0.6.1.dist-info/LICENSE
streamlit_dash-0.6.1.dist-info/METADATA
streamlit_dash-0.6.1.dist-info/WHEEL
streamlit_dash-0.6.1.dist-info/RECORD
