Metadata-Version: 2.1
Name: streamlit-dash
Version: 0.6.1
Summary: 🖼️ An image select component for Streamlit
License: MIT
Author: Onuralp SEZER
Author-email: thunderbirdtr@gmail.com
Requires-Python: >=3.8, !=2.7.*, !=3.0.*, !=3.1.*, !=3.2.*, !=3.3.*, !=3.4.*, !=3.5.*, !=3.6.*, !=3.7.*
Classifier: License :: OSI Approved :: MIT License
Classifier: Programming Language :: Python :: 3
Classifier: Programming Language :: Python :: 3.8
Classifier: Programming Language :: Python :: 3.9
Classifier: Programming Language :: Python :: 3.10
Classifier: Programming Language :: Python :: 3.11
Requires-Dist: streamlit (>=1.19.0,<2.0.0)
